sferriol/scb/__init__.py
sferriol/scb/asyncio_shared_circular_buffer.py
sferriol/scb/file_lock.py
sferriol/scb/shared_circular_buffer.py
sferriol/scb/shared_memory.py
sferriol_scb-0.2.0.dist-info/LICENSE
sferriol_scb-0.2.0.dist-info/METADATA
sferriol_scb-0.2.0.dist-info/WHEEL
sferriol_scb-0.2.0.dist-info/top_level.txt
sferriol_scb-0.2.0.dist-info/RECORD
